meteomoris/__init__.py
meteomoris/__main__.py
meteomoris/meteo.py
meteomoris-2.12.3.dist-info/LICENSE
meteomoris-2.12.3.dist-info/METADATA
meteomoris-2.12.3.dist-info/WHEEL
meteomoris-2.12.3.dist-info/entry_points.txt
meteomoris-2.12.3.dist-info/top_level.txt
meteomoris-2.12.3.dist-info/RECORD
