Metadata-Version: 2.2
Name: meteomoris
Version: 2.12.3
Summary: Package to get weather information about Mauritius from the official meteo website.
Home-page: https://github.com/Abdur-RahmaanJ/meteomoris
Author: Abdur-Rahmaan Janhangeer
Author-email: arj.python@gmail.com
Project-URL: Bug Reports, https://github.com/Abdur-RahmaanJ/meteomoris/issues
Project-URL: Source, https://github.com/Abdur-RahmaanJ/meteomoris/
Keywords: weather mauritius meteo
Classifier: Development Status :: 3 - Alpha
Classifier: Intended Audience :: Developers
Classifier: License :: OSI Approved :: MIT License
Classifier: Programming Language :: Python :: 3.4
Classifier: Programming Language :: Python :: 3.5
Classifier: Programming Language :: Python :: 3.6
Classifier: Programming Language :: Python :: 3.7
Classifier: Programming Language :: Python :: 3.8
Classifier: Programming Language :: Python :: 3.9
Classifier: Programming Language :: Python :: 3.10
Requires-Python: >=3.4
License-File: LICENSE
Requires-Dist: beautifulsoup4>=4.9.3
Requires-Dist: click>=7.1.2
Requires-Dist: requests>=2.20.0
Requires-Dist: rich>=11.2.0
Dynamic: author
Dynamic: author-email
Dynamic: classifier
Dynamic: description
Dynamic: description-content-type
Dynamic: home-page
Dynamic: keywords
Dynamic: project-url
Dynamic: requires-dist
Dynamic: requires-python
Dynamic: summary
